{
    "configurations": [
        {
            "name": "Linux",
            "includePath": [
								"${workspaceFolder}/src/**",
                "/usr/local/ws/include"
            ],
            "defines": [
                "_LINUX",
                "TRC"
            ],
            "compileCommands": "${workspaceFolder}/build/compile_commands.json",
            "compilerPath": "/usr/bin/g++-10",
            "cStandard": "c11",
            "cppStandard": "c++20",
            "browse": {
                "path": ["${workspaceFolder}"],
                "limitSymbolsToIncludedHeaders": true,
                "databaseFilename": ""
            },
            "configurationProvider": "linux-gcc-x64",
						"intelliSenseMode": "${default}",
            "C_Cpp.intelliSenseCacheSize": 0
        }
    ],
    "version": 4
}